geostatista/__init__.py
geostatista/tools.py
geostatista-0.1.6.dist-info/AUTHORS.rst
geostatista-0.1.6.dist-info/LICENSE.md
geostatista-0.1.6.dist-info/METADATA
geostatista-0.1.6.dist-info/WHEEL
geostatista-0.1.6.dist-info/top_level.txt
geostatista-0.1.6.dist-info/RECORD
