Metadata-Version: 2.1
Name: geostatista
Version: 0.1.6
Summary: statistics package
Home-page: https://github.com/MAfarrag/geostatista
Author: Mostafa Farrag
Author-email: moah.farag@gmail.come
License: GNU General Public License v3
Keywords: geospatial statistics,distributions
Classifier: Development Status :: 5 - Production/Stable
Classifier: Environment :: Console
Classifier: License :: OSI Approved :: GNU General Public License v3 (GPLv3)
Classifier: Natural Language :: English
Classifier: Programming Language :: Python :: 3
Classifier: Programming Language :: Python :: 3.7
Classifier: Programming Language :: Python :: 3.8
Classifier: Programming Language :: Python :: 3.9
Classifier: Intended Audience :: Science/Research
Classifier: Intended Audience :: Developers
License-File: LICENSE.md
License-File: AUTHORS.rst
Requires-Dist: loguru (>=0.6.0)
Requires-Dist: numpy (==1.24.1)
Requires-Dist: pip (>=22.3.1)
Requires-Dist: pyramids-gis (>=0.3.2)
Requires-Dist: statista (>=0.1.8)
